XAccess/__init__.py
XAccess/API/Actions.py
XAccess/API/Server.py
XAccess/API/__init__.py
XAccess/XSession/Session.py
XAccess/XSession/__init__.py
XAccess-1.0.dist-info/LICENSE
XAccess-1.0.dist-info/METADATA
XAccess-1.0.dist-info/WHEEL
XAccess-1.0.dist-info/top_level.txt
XAccess-1.0.dist-info/RECORD
