Metadata-Version: 2.1
Name: XAccess
Version: 1.0
Summary: Communication with the server using server and client
Home-page: https://github.com/Sepehr0Day/XAccess/
Author: Your Name
Author-email: sphrz2324@gmail.com
License: MIT
License-File: LICENSE
Requires-Dist: requests
Requires-Dist: colorama
